bte/__init__.py
bte/dvm/__init__.py
bte/dvm/collision.py
bte/dvm/distribution.py
bte/dvm/solver.py
bte/grad/GradEquation.py
bte/grad/GradEquationHybrid.py
bte/grad/__init__.py
bte/grad/collision_grad.py
bte/grad/distribution.py
bte/grad/indexs.py
bte/grad/operators.py
bte/utils/ERK.py
bte/utils/IMEX_RK.py
bte/utils/IMEX_RK2.py
bte/utils/__init__.py
bte/utils/distransfer.py
bte/utils/gas.py
bte/utils/indexs.py
bte/utils/limiter.py
bte/utils/operators.py
bte/utils/record.py
bte/utils/rescon.py
bte/utils/specials.py
bte/utils/trace.py
bte/utils/weno5.py
bte_pytorch-0.0.1.5rc0.dist-info/LICENSE
bte_pytorch-0.0.1.5rc0.dist-info/WHEEL
bte_pytorch-0.0.1.5rc0.dist-info/METADATA
bte_pytorch-0.0.1.5rc0.dist-info/RECORD
