Metadata-Version: 2.1
Name: bte-pytorch
Version: 0.0.1.5rc0
Summary: Fully Differentiable Boltzmann Transport Equation solver in PyTorch
Author-email: Zhengyi Li <lizhengyi.pku@gmail.com>
Requires-Python: >=3.7
Requires-Dist: torch >=1.9.0
Requires-Dist: numpy
Requires-Dist: scipy
Project-URL: Documentation, https://bte-pytorch.readthedocs.io/en/latest
Project-URL: Homepage, https://github.com/li-positive-one/bte-pytorch
